Metadata-Version: 1.0
Name: mymx
Version: 0.0.2
Summary: just test python pip module
Home-page: https://github.com/huangweibbk001/mymx
Author: huangweigang
Author-email: huangweibbk001@googlemail.com
License: MIT
Platform: UNKNOWN
